github_graphql_paginator-0.0.3.dist-info/licenses/COPYING
github_graphql_paginator-0.0.3.dist-info/licenses/COPYING.LESSER
githubgql/Client.py
githubgql/Clock.py
githubgql/Config.py
githubgql/Merger.py
githubgql/Paginator.py
githubgql/PathKey.py
githubgql/Query.py
githubgql/Results.py
githubgql/Schema.py
githubgql/__init__.py
githubgql/config.yml
githubgql/schema.docs.graphql
github_graphql_paginator-0.0.3.dist-info/METADATA
github_graphql_paginator-0.0.3.dist-info/WHEEL
github_graphql_paginator-0.0.3.dist-info/top_level.txt
github_graphql_paginator-0.0.3.dist-info/RECORD
