Metadata-Version: 2.4
Name: github-graphql-paginator
Version: 0.0.3
Summary: A simplified, opinionated way to access the GitHub GraphQL API
Author-email: Brian Gray <bgraymusic@gmail.com>
License-Expression: GPL-3.0-or-later
Project-URL: Homepage, https://github.com/bgraymusic/github-gql
Project-URL: Issues, https://github.com/bgraymusic/github-gql/issues
Classifier: Development Status :: 3 - Alpha
Classifier: Environment :: Web Environment
Classifier: Intended Audience :: Developers
Classifier: Operating System :: OS Independent
Classifier: Programming Language :: Python
Classifier: Programming Language :: Python :: 3
Classifier: Programming Language :: Python :: 3.10
Classifier: Programming Language :: Python :: 3.11
Classifier: Programming Language :: Python :: 3.12
Classifier: Programming Language :: Python :: 3.13
Classifier: Topic :: Software Development
Classifier: Topic :: Software Development :: Libraries
Classifier: Topic :: Software Development :: Libraries :: Python Modules
Requires-Python: <4.0,>=3.10
License-File: COPYING
License-File: COPYING.LESSER
Requires-Dist: gql[requests]
Requires-Dist: deepmerge
Requires-Dist: pyyaml
Requires-Dist: dill
Dynamic: license-file
